setup.py
django_geosimple.egg-info/PKG-INFO
django_geosimple.egg-info/SOURCES.txt
django_geosimple.egg-info/dependency_links.txt
django_geosimple.egg-info/requires.txt
django_geosimple.egg-info/top_level.txt
geosimple/__init__.py
geosimple/fields.py
geosimple/managers.py
geosimple/models.py
geosimple/utils.py
geosimple/tests/__init__.py
geosimple/tests/models.py
geosimple/tests/tests.py