Metadata-Version: 1.0
Name: django-geosimple
Version: 1.0.1
Summary: Simple Geohashing helpers
Home-page: http://github.com/dabapps/django-geosimple/
Author: Jamie Matthews
Author-email: jamie@dabapps.com
License: BSD
Platform: UNKNOWN
